license.md
pyb2b/__init__.py
pyb2b/console/airac.py
pyb2b/flight.py
pyb2b/flow.py
pyb2b/main.py
pyb2b/mixins.py
pyb2b/pkcs12.py
pyb2b/py.typed
pyb2b/reply.py
pyb2b/xml/CompleteAIXMDatasetRequest.xml
pyb2b/xml/FlightListByAerodromeRequest.xml
pyb2b/xml/FlightListByAirspaceRequest.xml
pyb2b/xml/FlightListByMeasureRequest.xml
pyb2b/xml/FlightPlanListRequest.xml
pyb2b/xml/FlightRetrievalRequest.xml
pyb2b/xml/RegulationListRequest.xml
pyb2b/xml/__init__.py
pyb2b-0.1.0.dist-info/METADATA
pyb2b-0.1.0.dist-info/WHEEL
pyb2b-0.1.0.dist-info/entry_points.txt
pyb2b-0.1.0.dist-info/RECORD
